django_misfit-0.0.4.dist-info/DESCRIPTION.rst
django_misfit-0.0.4.dist-info/METADATA
django_misfit-0.0.4.dist-info/metadata.json
django_misfit-0.0.4.dist-info/RECORD
django_misfit-0.0.4.dist-info/top_level.txt
django_misfit-0.0.4.dist-info/WHEEL
misfitapp/__init__.py
misfitapp/decorators.py
misfitapp/defaults.py
misfitapp/models.py
misfitapp/tasks.py
misfitapp/urls.py
misfitapp/utils.py
misfitapp/views.py
misfitapp/migrations/0001_initial.py
misfitapp/migrations/0002_auto_20151008_1530.py
misfitapp/migrations/0003_auto_20151009_1702.py
misfitapp/migrations/0004_increase_devicetype_maxlength.py
misfitapp/migrations/__init__.py
misfitapp/templates/misfit/error.html
misfitapp/templatetags/__init__.py
misfitapp/templatetags/misfit.py
misfitapp/tests/__init__.py
misfitapp/tests/base.py
misfitapp/tests/test_integration.py
misfitapp/tests/test_models.py
misfitapp/tests/test_tasks.py
misfitapp/tests/test_utils.py
