Metadata-Version: 2.0
Name: django-misfit
Version: 0.0.4
Summary: Django integration for python-misfit
Home-page: https://github.com/orcasgit/django-misfit/
Author: orcas
Author-email: bpitcher@orcasinc.com
License: License :: OSI Approved :: Apache Software License
Platform: UNKNOWN
Classifier: Development Status :: 3 - Alpha
Classifier: License :: OSI Approved :: Apache Software License
Classifier: Environment :: Web Environment
Classifier: Framework :: Django
Classifier: Intended Audience :: Developers
Classifier: Programming Language :: Python
Classifier: Programming Language :: Python :: 2
Classifier: Programming Language :: Python :: 2.7
Classifier: Programming Language :: Python :: 3
Classifier: Programming Language :: Python :: 3.3
Classifier: Programming Language :: Python :: 3.4
Classifier: Programming Language :: Python :: 3.5
Classifier: Programming Language :: Python :: Implementation :: PyPy
Requires-Dist: setuptools
Requires-Dist: celery (<3.2,>=3.1.0)
Requires-Dist: misfit (<0.4,>=0.3.1)
